Data_Analysis_Lib-2.0.dist-info/METADATA
Data_Analysis_Lib-2.0.dist-info/RECORD
Data_Analysis_Lib-2.0.dist-info/WHEEL
Data_Analysis_Lib-2.0.dist-info/top_level.txt
dataanalysislib/__init__.py
dataanalysislib/dataset.py
dataanalysislib/global_enums.py
dataanalysislib/global_funcs.py
dataanalysislib/pascoparser.py
dataanalysislib/xydatafit.py
dataanalysislib/xydataset.py
dataanalysislib/xyfit.py
