Metadata-Version: 2.1
Name: Data-Analysis-Lib
Version: 2.0
Summary: Open Source library developed for in-lab easy data analysis and processing.                     Intended for student use in experimental Physics labs.
Home-page: https://github.com/jeanyvesb9/DataAnalysisLib
Author: jeanyvesb9 and aguscaputobugallo
Author-email: jeanyvesb9@me.com
License: MIT
Download-URL: https://github.com/jeanyvesb9/DataAnalysisLib/archive/1.0.tar.gz
Keywords: data,analyis,physics
Platform: UNKNOWN
